senzing_abstract/__init__.py
senzing_abstract/constants.py
senzing_abstract/py.typed
senzing_abstract/szabstractfactory_abstract.py
senzing_abstract/szconfig_abstract.py
senzing_abstract/szconfigmanager_abstract.py
senzing_abstract/szdiagnostic_abstract.py
senzing_abstract/szengine_abstract.py
senzing_abstract/szengineflags.py
senzing_abstract/szerror.py
senzing_abstract/szhelpers.py
senzing_abstract/szproduct_abstract.py
senzing_truthset/__init__.py
senzing_truthset/customers.py
senzing_truthset/datasources.py
senzing_truthset/py.typed
senzing_truthset/references.py
senzing_truthset/watchlist.py
senzing_abstract-0.1.12.dist-info/LICENSE
senzing_abstract-0.1.12.dist-info/METADATA
senzing_abstract-0.1.12.dist-info/WHEEL
senzing_abstract-0.1.12.dist-info/top_level.txt
senzing_abstract-0.1.12.dist-info/RECORD
