Metadata-Version: 2.1
Name: senzing_abstract
Version: 0.1.12
Summary: Python SDK method definitions
Home-page: https://github.com/senzing-garage/sz-sdk-python-abstract
Author: senzing
Author-email: support@senzing.com
License: Apache 2
Project-URL: Bug Tracker, https://github.com/senzing-garage/sz-sdk-python-abstract/issues
Classifier: Programming Language :: Python :: 3
Classifier: License :: OSI Approved :: Apache Software License
Classifier: Operating System :: OS Independent
Requires-Python: >=3.9
License-File: LICENSE
